{
  "$schema": "https://schemas.wp.org/trunk/block.json",
  "apiVersion": 3,
  "name": "jurible/article-sommaire",
  "version": "1.0.0",
  "title": "Sommaire Article",
  "category": "jurible",
  "icon": "list-view",
  "description": "Sommaire dynamique généré à partir des titres H2 de l'article.",
  "keywords": [
    "sommaire",
    "table",
    "contents",
    "toc",
    "article"
  ],
  "supports": {
    "html": false,
    "multiple": false
  },
  "textdomain": "jurible-blocks-react",
  "editorScript": "file:./index.js",
  "editorStyle": "file:./index.css",
  "style": "file:./style-index.css",
  "render": "file:./render.php",
  "viewScript": "file:./view.js"
}